[
  {
    "platform" : "IPHONE_ARM64",
    "searchTime" : "2021-02-03T02:28:45.045Z[UTC]",
    "searchQuery" : "eric ung",
    "searchInteractionURIs" : [
      "spotify:user:1291480496",
      ""
    ]
  },
  {
    "platform" : "IPHONE_ARM64",
    "searchTime" : "2021-02-03T02:28:52.555Z[UTC]",
    "searchQuery" : "niyoosh",
    "searchInteractionURIs" : [
      "spotify:user:niyoosha"
    ]
  },
  {
    "platform" : "IPHONE_ARM64",
    "searchTime" : "2021-02-05T07:52:55.589Z[UTC]",
    "searchQuery" : "dd",
    "searchInteractionURIs" : [
      ""
    ]
  },
  {
    "platform" : "IPHONE_ARM64",
    "searchTime" : "2021-02-05T18:37:53.645Z[UTC]",
    "searchQuery" : "d-d-d",
    "searchInteractionURIs" : [
      "spotify:track:3U764c5XbUqjr408oTrjfy"
    ]
  },
  {
    "platform" : "IPHONE_ARM64",
    "searchTime" : "2021-02-07T02:57:14.777Z[UTC]",
    "searchQuery" : "taylor swift",
    "searchInteractionURIs" : [
      "spotify:artist:06HL4z0CvFAxyc27GXpf02",
      ""
    ]
  },
  {
    "platform" : "IPHONE_ARM64",
    "searchTime" : "2021-02-07T03:05:43.551Z[UTC]",
    "searchQuery" : "what makes ",
    "searchInteractionURIs" : [
      "spotify:track:4cluDES4hQEUhmXj6TXkSo",
      "spotify:track:4cluDES4hQEUhmXj6TXkSo"
    ]
  },
  {
    "platform" : "IPHONE_ARM64",
    "searchTime" : "2021-02-07T21:13:11.194Z[UTC]",
    "searchQuery" : "weekn",
    "searchInteractionURIs" : [
      "spotify:artist:1Xyo4u8uXC1ZmMpatF05PJ"
    ]
  },
  {
    "platform" : "IPHONE_ARM64",
    "searchTime" : "2021-02-13T01:04:09.860Z[UTC]",
    "searchQuery" : "run awa",
    "searchInteractionURIs" : [
      "spotify:playlist:3dDLwUJTfJevb5JGSp2H3v",
      ""
    ]
  },
  {
    "platform" : "IPHONE_ARM64",
    "searchTime" : "2021-02-25T03:11:47.563Z[UTC]",
    "searchQuery" : "dont leave me",
    "searchInteractionURIs" : [
      "spotify:track:3zIG0WuI5RoJsFYnErkFDU"
    ]
  },
  {
    "platform" : "IPHONE_ARM64",
    "searchTime" : "2021-03-02T21:21:54.915Z[UTC]",
    "searchQuery" : "serendi",
    "searchInteractionURIs" : [
      "spotify:track:5cQB9fbuQCz4muQUFkv3rR"
    ]
  },
  {
    "platform" : "IPHONE_ARM64",
    "searchTime" : "2021-03-08T04:34:30.398Z[UTC]",
    "searchQuery" : "house ",
    "searchInteractionURIs" : [
      "spotify:track:4BMbbfwW9GLl9b05ecYKVa",
      "spotify:track:4BMbbfwW9GLl9b05ecYKVa",
      "spotify:track:4BMbbfwW9GLl9b05ecYKVa",
      "spotify:track:4BMbbfwW9GLl9b05ecYKVa",
      "spotify:track:4BMbbfwW9GLl9b05ecYKVa",
      "spotify:track:4BMbbfwW9GLl9b05ecYKVa",
      ""
    ]
  },
  {
    "platform" : "IPHONE_ARM64",
    "searchTime" : "2021-03-10T01:29:36.993Z[UTC]",
    "searchQuery" : "dddance",
    "searchInteractionURIs" : [
      "spotify:artist:5r1tUTxVSgvBHnoDuDODPH",
      "spotify:playlist:694eMpgcPcdpyCoFm6m0qm"
    ]
  },
  {
    "platform" : "IPHONE_ARM64",
    "searchTime" : "2021-03-10T21:14:47.277Z[UTC]",
    "searchQuery" : "sista",
    "searchInteractionURIs" : [
      "spotify:artist:2wTLheTmMcFCA4hdY8hZJP",
      ""
    ]
  },
  {
    "platform" : "IPHONE_ARM64",
    "searchTime" : "2021-03-11T02:15:06.764Z[UTC]",
    "searchQuery" : "la di",
    "searchInteractionURIs" : [
      "spotify:track:60M8FSYZP8MA0Wy2huOADL",
      "spotify:track:60M8FSYZP8MA0Wy2huOADL",
      ""
    ]
  },
  {
    "platform" : "IPHONE_ARM64",
    "searchTime" : "2021-03-11T02:15:21.741Z[UTC]",
    "searchQuery" : "sm",
    "searchInteractionURIs" : [
      ""
    ]
  },
  {
    "platform" : "IPHONE_ARM64",
    "searchTime" : "2021-03-11T02:15:42.585Z[UTC]",
    "searchQuery" : "run awa",
    "searchInteractionURIs" : [
      "spotify:playlist:2s0BOx4Q8ugkUrIqnadQvr"
    ]
  },
  {
    "platform" : "IPHONE_ARM64",
    "searchTime" : "2021-03-11T16:29:08.250Z[UTC]",
    "searchQuery" : "nekkoya",
    "searchInteractionURIs" : [
      ""
    ]
  },
  {
    "platform" : "IPHONE_ARM64",
    "searchTime" : "2021-03-11T16:49:59.151Z[UTC]",
    "searchQuery" : "nekko",
    "searchInteractionURIs" : [
      "spotify:track:5kprxqsCHKz3c6KMIRQrNL"
    ]
  },
  {
    "platform" : "IPHONE_ARM64",
    "searchTime" : "2021-03-14T06:18:23.210Z[UTC]",
    "searchQuery" : "bts",
    "searchInteractionURIs" : [
      "spotify:artist:3Nrfpe0tUJi4K4DXYWgMUX",
      "spotify:artist:3Nrfpe0tUJi4K4DXYWgMUX",
      ""
    ]
  },
  {
    "platform" : "IPHONE_ARM64",
    "searchTime" : "2021-03-14T06:53:11.673Z[UTC]",
    "searchQuery" : "blackpink",
    "searchInteractionURIs" : [
      "spotify:artist:41MozSoPIsD1dJM0CLPjZF",
      ""
    ]
  },
  {
    "platform" : "IPHONE_ARM64",
    "searchTime" : "2021-03-14T06:58:30.188Z[UTC]",
    "searchQuery" : "izone ",
    "searchInteractionURIs" : [
    ]
  },
  {
    "platform" : "IPHONE_ARM64",
    "searchTime" : "2021-03-14T06:58:30.265Z[UTC]",
    "searchQuery" : "izone",
    "searchInteractionURIs" : [
      "spotify:track:0CnpSTdL9l5vQM4YnzXtyo",
      ""
    ]
  },
  {
    "platform" : "IPHONE_ARM64",
    "searchTime" : "2021-03-14T07:00:04.280Z[UTC]",
    "searchQuery" : "not shy",
    "searchInteractionURIs" : [
      "spotify:track:4ecVWqbtW6phQGpZMAyqIU",
      ""
    ]
  },
  {
    "platform" : "IPHONE_ARM64",
    "searchTime" : "2021-03-14T07:00:30.422Z[UTC]",
    "searchQuery" : "feel ",
    "searchInteractionURIs" : [
      "spotify:album:3NQBPabmRm3LzVcmtkTLfo",
      ""
    ]
  },
  {
    "platform" : "IPHONE_ARM64",
    "searchTime" : "2021-03-14T07:00:48.333Z[UTC]",
    "searchQuery" : "f",
    "searchInteractionURIs" : [
      ""
    ]
  },
  {
    "platform" : "IPHONE_ARM64",
    "searchTime" : "2021-03-15T13:48:12.708Z[UTC]",
    "searchQuery" : "bald",
    "searchInteractionURIs" : [
      "spotify:show:36SPp0UJlpM9TDacDHMhEC"
    ]
  },
  {
    "platform" : "IPHONE_ARM64",
    "searchTime" : "2021-03-16T03:25:55.626Z[UTC]",
    "searchQuery" : "landon",
    "searchInteractionURIs" : [
      "spotify:artist:2WROyFfIOmKtRopsTrIL52"
    ]
  },
  {
    "platform" : "IPHONE_ARM64",
    "searchTime" : "2021-03-18T04:50:44.896Z[UTC]",
    "searchQuery" : "landon",
    "searchInteractionURIs" : [
      "spotify:search:artists:landon"
    ]
  },
  {
    "platform" : "IPHONE_ARM64",
    "searchTime" : "2021-03-18T04:50:49.458Z[UTC]",
    "searchQuery" : "landon",
    "searchInteractionURIs" : [
      "spotify:artist:3j4ihH7xANVDGQhcDFJby7"
    ]
  },
  {
    "platform" : "IPHONE",
    "searchTime" : "2021-04-01T16:07:38.153Z[UTC]",
    "searchQuery" : "d",
    "searchInteractionURIs" : [
    ]
  },
  {
    "platform" : "IPHONE",
    "searchTime" : "2021-04-01T18:57:07.737Z[UTC]",
    "searchQuery" : "weeekly",
    "searchInteractionURIs" : [
      "spotify:artist:73B9bjqS2Z5KLXNGqXf64m"
    ]
  },
  {
    "platform" : "IPHONE",
    "searchTime" : "2021-04-16T07:40:44.064Z[UTC]",
    "searchQuery" : "talking to",
    "searchInteractionURIs" : [
      "spotify:track:161DnLWsx1i3u1JT05lzqU"
    ]
  },
  {
    "platform" : "IPHONE",
    "searchTime" : "2021-04-16T08:12:25.111Z[UTC]",
    "searchQuery" : "dej",
    "searchInteractionURIs" : [
      "spotify:playlist:64JF2RlP8wtwGewYg2md2B"
    ]
  },
  {
    "platform" : "IPHONE",
    "searchTime" : "2021-04-16T08:12:37.010Z[UTC]",
    "searchQuery" : "oli",
    "searchInteractionURIs" : [
      "spotify:artist:1McMsnEElThX1knmY4oliG"
    ]
  },
  {
    "platform" : "IPHONE",
    "searchTime" : "2021-04-17T01:39:37.726Z[UTC]",
    "searchQuery" : "niyoosha ",
    "searchInteractionURIs" : [
      "spotify:user:niyoosha"
    ]
  },
  {
    "platform" : "IPHONE",
    "searchTime" : "2021-04-18T01:25:05.889Z[UTC]",
    "searchQuery" : "den",
    "searchInteractionURIs" : [
      "spotify:artist:6fxyWrfmjcbj5d12gXeiNV"
    ]
  },
  {
    "platform" : "IPHONE",
    "searchTime" : "2021-04-18T01:25:10.449Z[UTC]",
    "searchQuery" : "de",
    "searchInteractionURIs" : [
      "spotify:track:61KpQadow081I2AsbeLcsb"
    ]
  },
  {
    "platform" : "IPHONE",
    "searchTime" : "2021-04-18T02:06:08.894Z[UTC]",
    "searchQuery" : "discovery",
    "searchInteractionURIs" : [
      "spotify:playlist:37i9dQZEVXcGUFoIE1AEq8"
    ]
  },
  {
    "platform" : "IPHONE",
    "searchTime" : "2021-04-19T16:04:36.291Z[UTC]",
    "searchQuery" : "call me ",
    "searchInteractionURIs" : [
      "spotify:track:67BtfxlNbhBmCDR2L2l8qd"
    ]
  },
  {
    "platform" : "IPHONE",
    "searchTime" : "2021-04-19T16:06:10.220Z[UTC]",
    "searchQuery" : "dej",
    "searchInteractionURIs" : [
      "spotify:track:61KpQadow081I2AsbeLcsb",
      "spotify:track:61KpQadow081I2AsbeLcsb"
    ]
  },
  {
    "platform" : "IPHONE",
    "searchTime" : "2021-04-20T19:20:34.120Z[UTC]",
    "searchQuery" : "cult 45",
    "searchInteractionURIs" : [
      "spotify:track:1ACZpHI5vZ5Ea4xGlkdGWM",
      "spotify:track:1ACZpHI5vZ5Ea4xGlkdGWM"
    ]
  },
  {
    "platform" : "IPHONE",
    "searchTime" : "2021-04-20T20:52:37.649Z[UTC]",
    "searchQuery" : "good to",
    "searchInteractionURIs" : [
      "spotify:track:2ujZatFh8uZMkiBTu2z7AH"
    ]
  },
  {
    "platform" : "IPHONE",
    "searchTime" : "2021-04-20T20:52:46.668Z[UTC]",
    "searchQuery" : "momm",
    "searchInteractionURIs" : [
      "spotify:track:1LNlfvPQmB0cqYJQQskZ8x"
    ]
  },
  {
    "platform" : "IPHONE",
    "searchTime" : "2021-04-22T02:09:58.389Z[UTC]",
    "searchQuery" : "azer elegante",
    "searchInteractionURIs" : [
      "spotify:track:4sLu61mcZkSm35e5luDwjx"
    ]
  },
  {
    "platform" : "IPHONE",
    "searchTime" : "2021-04-22T03:49:18.361Z[UTC]",
    "searchQuery" : "speechless",
    "searchInteractionURIs" : [
      "spotify:track:3GJ4hzg4lrGwU51Y3VARbF"
    ]
  },
  {
    "platform" : "IPHONE",
    "searchTime" : "2021-04-24T18:58:54.289Z[UTC]",
    "searchQuery" : "kura",
    "searchInteractionURIs" : [
      "spotify:album:5FMslDParbcWQ7o5FQqCWf"
    ]
  },
  {
    "platform" : "IPHONE",
    "searchTime" : "2021-04-24T18:59:18.299Z[UTC]",
    "searchQuery" : "im so ",
    "searchInteractionURIs" : [
      "spotify:track:6oZee3RwM7GHykYHZeb7GT",
      "spotify:track:6oZee3RwM7GHykYHZeb7GT"
    ]
  },
  {
    "platform" : "IPHONE",
    "searchTime" : "2021-04-25T09:06:55.628Z[UTC]",
    "searchQuery" : "lay me down",
    "searchInteractionURIs" : [
      "spotify:track:74sb4Gib0cL3TQeCjYF8vh",
      "spotify:track:64GRDrL1efgXclrhVCeuA0",
      "spotify:track:74sb4Gib0cL3TQeCjYF8vh",
      "spotify:track:74sb4Gib0cL3TQeCjYF8vh",
      "spotify:track:74sb4Gib0cL3TQeCjYF8vh"
    ]
  },
  {
    "platform" : "IPHONE",
    "searchTime" : "2021-04-28T19:49:33.526Z[UTC]",
    "searchQuery" : "gee",
    "searchInteractionURIs" : [
      "spotify:track:0t7kjpVLgOYITrSfFCoBEA"
    ]
  }
]